idpartner/__init__.py
python_oidc_client-0.0.1.dist-info/LICENSE.txt
python_oidc_client-0.0.1.dist-info/METADATA
python_oidc_client-0.0.1.dist-info/WHEEL
python_oidc_client-0.0.1.dist-info/top_level.txt
python_oidc_client-0.0.1.dist-info/RECORD
